{
  "challengeId": "C41",
  "name": "CHALLENGE 41",
  "subtitle": "Linux Administration & Shell Scripting",
  "description": "Covers Linux CLI, package managers (APT/YUM), user management, file permissions, shell scripting basics, variables, conditionals, loops, and environment variables.",
  "questions": [
    {
      "id": "C41_Q1",
      "question": "What is the CLI in Linux?",
      "options": [
        "Command Line Interface for text-based interaction with the OS",
        "Computer Language Interpreter",
        "Common Linux Installation",
        "Cloud Linux Integration"
      ],
      "correctIndex": 0,
      "explanation": "CLI (Command Line Interface) is a text-based interface that allows users to interact with the operating system by typing commands."
    },
    {
      "id": "C41_Q2",
      "question": "What is the difference between a regular user and root user in Linux?",
      "options": [
        "Regular user is faster than root",
        "Root user has unlimited administrative privileges; regular user has limited permissions",
        "Root user can only read files",
        "There is no difference"
      ],
      "correctIndex": 1,
      "explanation": "The root user has unlimited administrative privileges and can perform any action on the system. Regular users have limited permissions for security."
    },
    {
      "id": "C41_Q3",
      "question": "What is a package manager in Linux?",
      "options": [
        "Software that automates installation, upgrading, and removal of software packages",
        "A tool for creating compressed archives",
        "A graphical file explorer",
        "A network monitoring tool"
      ],
      "correctIndex": 0,
      "explanation": "A package manager automates the process of installing, upgrading, configuring, and removing software packages from repositories."
    },
    {
      "id": "C41_Q4",
      "question": "What does APT stand for in Debian-based systems?",
      "options": [
        "Advanced Package Tool",
        "Advanced Programming Tool",
        "Application Packaging Technology",
        "Automated Process Tracker"
      ],
      "correctIndex": 0,
      "explanation": "APT stands for Advanced Package Tool. It is a package management system used by Debian and Ubuntu-based distributions."
    },
    {
      "id": "C41_Q5",
      "question": "What command updates the package index before installing new packages on Ubuntu?",
      "options": [
        "sudo apt update",
        "apt-get install",
        "yum refresh",
        "dnf sync"
      ],
      "correctIndex": 0,
      "explanation": "'sudo apt update' updates the package index from repositories, ensuring you have the latest package information before installing or upgrading."
    },
    {
      "id": "C41_Q6",
      "question": "Which package manager is commonly used on RHEL, CentOS, and Fedora?",
      "options": [
        "YUM or DNF",
        "APT",
        "Pacman",
        "Zypper"
      ],
      "correctIndex": 0,
      "explanation": "YUM (Yellowdog Updater Modified) and DNF (Dandified YUM) are the package managers used on Red Hat-based systems like RHEL, CentOS, and Fedora."
    },
    {
      "id": "C41_Q7",
      "question": "What does 'sudo' command do?",
      "options": [
        "Shutdown the system",
        "Run a command with superuser (root) privileges",
        "Show disk usage",
        "Sort files by name"
      ],
      "correctIndex": 1,
      "explanation": "'sudo' (superuser do) allows a permitted user to execute a command as the superuser or another user with appropriate privileges."
    },
    {
      "id": "C41_Q8",
      "question": "What are the three types of file permissions in Linux?",
      "options": [
        "Read, Write, Execute",
        "Create, Delete, Modify",
        "Open, Close, Save",
        "Copy, Move, Rename"
      ],
      "correctIndex": 0,
      "explanation": "Linux file permissions are Read (r), Write (w), and Execute (x). These can be set for owner, group, and others."
    },
    {
      "id": "C41_Q9",
      "question": "What are the three categories of access for file permissions?",
      "options": [
        "Owner, Group, Others",
        "Admin, User, Guest",
        "Local, Remote, Network",
        "System, Application, User"
      ],
      "correctIndex": 0,
      "explanation": "File permissions in Linux are applied to three categories: Owner (u), Group (g), and Others (o)."
    },
    {
      "id": "C41_Q10",
      "question": "What command changes file permissions in Linux?",
      "options": [
        "chmod",
        "chown",
        "chperm",
        "setfacl"
      ],
      "correctIndex": 0,
      "explanation": "'chmod' (change mode) is used to change the permissions of files or directories in Linux."
    },
    {
      "id": "C41_Q11",
      "question": "What does 'chmod 755 file.txt' do?",
      "options": [
        "Changes owner of the file",
        "Sets permissions: owner read/write/execute, group/others read/execute",
        "Deletes the file",
        "Copies the file 755 times"
      ],
      "correctIndex": 1,
      "explanation": "755 in octal means: Owner (7=rwx), Group (5=r-x), Others (5=r-x). Owner can read, write, execute; others can read and execute."
    },
    {
      "id": "C41_Q12",
      "question": "What command changes file ownership in Linux?",
      "options": [
        "chown",
        "chmod",
        "chgrp",
        "usermod"
      ],
      "correctIndex": 0,
      "explanation": "'chown' (change owner) is used to change the user and/or group ownership of a file or directory."
    },
    {
      "id": "C41_Q13",
      "question": "What does 'ls -la' command display?",
      "options": [
        "All files including hidden ones in long listing format",
        "Only hidden files",
        "Large files only",
        "Last accessed files"
      ],
      "correctIndex": 0,
      "explanation": "'ls -la' lists all files (-a includes hidden files starting with .) in long format (-l) showing permissions, owner, size, and date."
    },
    {
      "id": "C41_Q14",
      "question": "What is the shebang line in a shell script?",
      "options": [
        "The first line starting with #! that specifies which interpreter to use",
        "A comment line describing the script",
        "A line that ends the script",
        "A debugging statement"
      ],
      "correctIndex": 0,
      "explanation": "The shebang (#!), also called hashbang, is the first line of a script that tells the system which interpreter (like /bin/bash) to use."
    },
    {
      "id": "C41_Q15",
      "question": "What is the typical shebang line for a Bash script?",
      "options": [
        "#bash",
        "#!/bin/bash",
        "/bin/bash",
        "# shell=bash"
      ],
      "correctIndex": 1,
      "explanation": "'#!/bin/bash' is the standard shebang for Bash scripts, indicating that the /bin/bash interpreter should execute the script."
    },
    {
      "id": "C41_Q16",
      "question": "How do you make a shell script executable?",
      "options": [
        "cp script.sh /bin",
        "exec script.sh",
        "chmod +x script.sh",
        "run script.sh"
      ],
      "correctIndex": 2,
      "explanation": "'chmod +x script.sh' adds execute permission to the script, allowing it to be run directly using './script.sh'."
    },
    {
      "id": "C41_Q17",
      "question": "What is a shell variable?",
      "options": [
        "A type of shellfish",
        "A command to exit the shell",
        "A named storage location that holds data for use in scripts",
        "A user interface element"
      ],
      "correctIndex": 2,
      "explanation": "A shell variable is a named storage location that can hold text or numbers, used to store and manipulate data in shell scripts."
    },
    {
      "id": "C41_Q18",
      "question": "How do you assign a value to a variable in Bash?",
      "options": [
        "let name = value",
        "set name to value",
        "name=value",
        "var(name)=value"
      ],
      "correctIndex": 2,
      "explanation": "In Bash, variables are assigned using 'name=value' without spaces around the equals sign. Example: myvar=hello"
    },
    {
      "id": "C41_Q19",
      "question": "How do you reference a variable in Bash?",
      "options": [
        "variable",
        "$variable",
        "@variable",
        "%variable%"
      ],
      "correctIndex": 1,
      "explanation": "Variables are referenced using the $ prefix, like $variable or ${variable}. The $ tells the shell to substitute the variable's value."
    },
    {
      "id": "C41_Q20",
      "question": "What is the purpose of the PATH environment variable?",
      "options": [
        "To store passwords",
        "To specify directories where the system looks for executable programs",
        "To define network routes",
        "To set the desktop wallpaper"
      ],
      "correctIndex": 1,
      "explanation": "PATH is an environment variable that lists directories where the shell searches for executable programs when you type a command."
    },
    {
      "id": "C41_Q21",
      "question": "What does the 'if' statement do in shell scripting?",
      "options": [
        "Imports external files",
        "Defines a function",
        "Executes code conditionally based on a test expression",
        "Creates a loop"
      ],
      "correctIndex": 2,
      "explanation": "The 'if' statement allows conditional execution of code blocks based on whether a test expression evaluates to true or false."
    },
    {
      "id": "C41_Q22",
      "question": "What is the syntax for a basic if statement in Bash?",
      "options": [
        "if (condition) { commands }",
        "if condition then commands end",
        "if [ condition ]; then commands; fi",
        "if: condition { commands }"
      ],
      "correctIndex": 2,
      "explanation": "Bash uses 'if [ condition ]; then commands; fi' syntax. The square brackets are a shorthand for the 'test' command."
    },
    {
      "id": "C41_Q23",
      "question": "What does the 'fi' keyword do in Bash?",
      "options": [
        "Starts a file operation",
        "Finds files",
        "Ends an if statement",
        "Formats input"
      ],
      "correctIndex": 2,
      "explanation": "'fi' (if spelled backwards) marks the end of an if statement in Bash, just like 'end if' in other languages."
    },
    {
      "id": "C41_Q24",
      "question": "What is a for loop used for in shell scripting?",
      "options": [
        "Testing network connectivity",
        "Formatting disk drives",
        "Iterating over a list of items and executing commands for each",
        "Finding files"
      ],
      "correctIndex": 2,
      "explanation": "A for loop iterates over a list of items (files, numbers, strings) and executes a block of commands for each item in the list."
    },
    {
      "id": "C41_Q25",
      "question": "What is a while loop in shell scripting?",
      "options": [
        "A loop that runs a specific number of times",
        "A loop for file processing only",
        "A loop that continues as long as a condition is true",
        "A deprecated feature"
      ],
      "correctIndex": 2,
      "explanation": "A while loop repeatedly executes commands as long as the specified condition evaluates to true. It stops when the condition becomes false."
    },
    {
      "id": "C41_Q26",
      "question": "What does the 'echo' command do?",
      "options": [
        "Deletes files",
        "Displays text or variable values to the terminal",
        "Edits configuration files",
        "Encrypts data"
      ],
      "correctIndex": 1,
      "explanation": "'echo' outputs text strings or variable values to the terminal. It's commonly used for printing messages or debugging."
    },
    {
      "id": "C41_Q27",
      "question": "How do you get command output into a variable?",
      "options": [
        "var = command",
        "var=$(command) or var=`command`",
        "set var = command",
        "var <- command"
      ],
      "correctIndex": 1,
      "explanation": "Command substitution uses $(command) or backticks `command` to capture command output into a variable. Example: date=$(date)"
    },
    {
      "id": "C41_Q28",
      "question": "What does the 'cd' command do?",
      "options": [
        "Copies directories",
        "Creates directories",
        "Changes the current working directory",
        "Counts disk usage"
      ],
      "correctIndex": 2,
      "explanation": "'cd' (change directory) changes the current working directory to the specified path. Example: cd /home/user"
    },
    {
      "id": "C41_Q29",
      "question": "What does 'cd ~' do?",
      "options": [
        "Goes to the previous directory",
        "Lists all directories",
        "Goes to the user's home directory",
        "Creates a home directory"
      ],
      "correctIndex": 2,
      "explanation": "The tilde (~) represents the current user's home directory. 'cd ~' takes you directly to your home directory."
    },
    {
      "id": "C41_Q30",
      "question": "What does 'pwd' command display?",
      "options": [
        "Password of the current user",
        "Processes currently running",
        "Present Working Directory (current directory path)",
        "Pending write operations"
      ],
      "correctIndex": 2,
      "explanation": "'pwd' (print working directory) displays the full path of the current directory you're in."
    },
    {
      "id": "C41_Q31",
      "question": "What does 'mkdir' command do?",
      "options": [
        "Makes a file executable",
        "Moves a directory",
        "Creates a new directory",
        "Modifies directory permissions"
      ],
      "correctIndex": 2,
      "explanation": "'mkdir' (make directory) creates new directories. Example: mkdir newfolder creates a directory called 'newfolder'."
    },
    {
      "id": "C41_Q32",
      "question": "What does 'rm' command do?",
      "options": [
        "Renames files",
        "Reads mail",
        "Removes files or directories",
        "Runs make"
      ],
      "correctIndex": 2,
      "explanation": "'rm' (remove) deletes files. 'rm -r' removes directories recursively. Use with caution as deleted files are not sent to trash."
    },
    {
      "id": "C41_Q33",
      "question": "What does 'cp' command do?",
      "options": [
        "Changes permissions",
        "Compiles programs",
        "Creates processes",
        "Copies files or directories"
      ],
      "correctIndex": 3,
      "explanation": "'cp' (copy) copies files or directories from source to destination. Example: cp file1.txt file2.txt"
    },
    {
      "id": "C41_Q34",
      "question": "What does 'mv' command do?",
      "options": [
        "Mounts volumes",
        "Makes variables",
        "Views memory",
        "Moves or renames files and directories"
      ],
      "correctIndex": 3,
      "explanation": "'mv' (move) moves files/directories to a new location or renames them. Example: mv oldname newname"
    },
    {
      "id": "C41_Q35",
      "question": "What does 'cat' command do?",
      "options": [
        "Changes attributes",
        "Catches signals",
        "Categorizes files",
        "Concatenates and displays file contents"
      ],
      "correctIndex": 3,
      "explanation": "'cat' (concatenate) displays file contents or combines multiple files. Example: cat file.txt shows the file's contents."
    },
    {
      "id": "C41_Q36",
      "question": "What does 'grep' command do?",
      "options": [
        "Groups files",
        "Graphs data",
        "Gets remote files",
        "Searches for text patterns in files"
      ],
      "correctIndex": 3,
      "explanation": "'grep' searches for lines matching a pattern in files. Example: grep 'error' log.txt finds lines containing 'error'."
    },
    {
      "id": "C41_Q37",
      "question": "What is the purpose of piping (|) in Linux?",
      "options": [
        "Creates a backup",
        "Prints to a printer",
        "Pauses command execution",
        "Sends output of one command as input to another"
      ],
      "correctIndex": 3,
      "explanation": "The pipe symbol (|) takes the output of the command on the left and passes it as input to the command on the right."
    },
    {
      "id": "C41_Q38",
      "question": "What does '>' do in a command?",
      "options": [
        "Compares numbers",
        "Appends to a file",
        "Runs command in background",
        "Redirects output to a file (overwrite)"
      ],
      "correctIndex": 3,
      "explanation": ">' redirects command output to a file, overwriting existing content. Example: echo 'hello' > file.txt"
    },
    {
      "id": "C41_Q39",
      "question": "What does '>>' do in a command?",
      "options": [
        "Shifts bits",
        "Compares strings",
        "Creates a symbolic link",
        "Redirects output to a file (append)"
      ],
      "correctIndex": 3,
      "explanation": ">> redirects command output to a file, appending to existing content instead of overwriting."
    },
    {
      "id": "C41_Q40",
      "question": "What is a symbolic link (symlink) in Linux?",
      "options": [
        "A special type of file that points to another file or directory",
        "A secure connection",
        "A system log",
        "A type of shell"
      ],
      "correctIndex": 0,
      "explanation": "A symbolic link is a special file that serves as a reference to another file or directory, similar to a shortcut."
    },
    {
      "id": "C41_Q41",
      "question": "What command creates a symbolic link?",
      "options": [
        "link",
        "ln -s",
        "symlink",
        "mklink"
      ],
      "correctIndex": 1,
      "explanation": "'ln -s' creates a symbolic link. Example: ln -s /path/to/file /path/to/link creates a symlink pointing to the file."
    },
    {
      "id": "C41_Q42",
      "question": "What does 'whoami' command display?",
      "options": [
        "The hostname of the system",
        "The IP address",
        "The system time",
        "The current username"
      ],
      "correctIndex": 3,
      "explanation": "'whoami' displays the username of the currently logged-in user running the command."
    },
    {
      "id": "C41_Q43",
      "question": "What does 'id' command show?",
      "options": [
        "Process IDs",
        "System hardware ID",
        "Network interface IDs",
        "User ID, group ID, and group memberships"
      ],
      "correctIndex": 3,
      "explanation": "'id' displays the user ID (UID), group ID (GID), and all groups that the current user belongs to."
    },
    {
      "id": "C41_Q44",
      "question": "What does 'touch' command do?",
      "options": [
        "Tests network connectivity",
        "Changes file type",
        "Transfers files",
        "Creates an empty file or updates timestamp"
      ],
      "correctIndex": 3,
      "explanation": "'touch' creates an empty file if it doesn't exist, or updates the access/modification timestamps if it does."
    },
    {
      "id": "C41_Q45",
      "question": "What does 'find' command do?",
      "options": [
        "Finds and replaces text",
        "Searches for files and directories based on criteria",
        "Finds running processes",
        "Finds network connections"
      ],
      "correctIndex": 1,
      "explanation": "'find' searches for files and directories in a directory hierarchy based on various criteria like name, size, or modification time."
    },
    {
      "id": "C41_Q46",
      "question": "What does 'ps' command display?",
      "options": [
        "Disk space usage",
        "Currently running processes",
        "Network ports",
        "System packages"
      ],
      "correctIndex": 1,
      "explanation": "'ps' (process status) displays information about currently running processes. 'ps aux' shows all processes in detail."
    },
    {
      "id": "C41_Q47",
      "question": "What does 'kill' command do?",
      "options": [
        "Deletes files permanently",
        "Terminates a process by PID",
        "Shuts down the system",
        "Removes users"
      ],
      "correctIndex": 1,
      "explanation": "'kill' sends a signal to terminate a process using its Process ID (PID). Example: kill 1234 stops process with PID 1234."
    },
    {
      "id": "C41_Q48",
      "question": "What does 'df' command show?",
      "options": [
        "Directory files",
        "Disk space usage of filesystems",
        "Deleted files",
        "Difference between files"
      ],
      "correctIndex": 1,
      "explanation": "'df' (disk free) displays disk space usage information for all mounted filesystems. 'df -h' shows human-readable sizes."
    },
    {
      "id": "C41_Q49",
      "question": "What does 'du' command show?",
      "options": [
        "Duplicate files",
        "Disk usage of files and directories",
        "Dynamic updates",
        "Device usage"
      ],
      "correctIndex": 1,
      "explanation": "'du' (disk usage) estimates file and directory space usage. 'du -sh directory' shows total size of a directory."
    },
    {
      "id": "C41_Q50",
      "question": "What is the purpose of comments in shell scripts?",
      "options": [
        "To execute special commands",
        "To document and explain code for human readers",
        "To import libraries",
        "To define variables"
      ],
      "correctIndex": 1,
      "explanation": "Comments (lines starting with #) are ignored by the shell and serve to document the script, making it easier to understand and maintain."
    }
  ]
}
